django_pylabels/__init__.py
django_pylabels/actions.py
django_pylabels/admin.py
django_pylabels/apps.py
django_pylabels/get_label_specification.py
django_pylabels/save_to_buffer.py
django_pylabels/urls.py
django_pylabels/utils.py
django_pylabels/view_mixins.py
django_pylabels/management/commands/__init__.py
django_pylabels/management/commands/prepare.py
django_pylabels/migrations/0001_initial.py
django_pylabels/migrations/0002_labelspecification_created_and_more.py
django_pylabels/migrations/0003_rename_updated_labelspecification_modified.py
django_pylabels/migrations/0004_alter_labelspecification_label_description_and_more.py
django_pylabels/migrations/__init__.py
django_pylabels/models/__init__.py
django_pylabels/models/label_history.py
django_pylabels/models/label_specification.py
django_pylabels/templates/print_labels_form.html
django_pylabels-0.1.2.dist-info/LICENSE
django_pylabels-0.1.2.dist-info/METADATA
django_pylabels-0.1.2.dist-info/WHEEL
django_pylabels-0.1.2.dist-info/top_level.txt
django_pylabels-0.1.2.dist-info/RECORD
