Metadata-Version: 2.1
Name: django-pylabels
Version: 0.1.2
Summary: Use pylabels2 in Django
Author-email: Erik van Widenfelt <ew2789@gmail.com>
License:                     GNU GENERAL PUBLIC LICENSE
Keywords: Django labels avery pylabels2
Classifier: Development Status :: 5 - Production/Stable
Classifier: License :: OSI Approved :: GNU General Public License v3 or later (GPLv3+)
Classifier: Operating System :: OS Independent
Classifier: Programming Language :: Python
Requires-Python: >=3.12
License-File: LICENSE
Requires-Dist: pylabels2
